microsoft_agents_m365copilot/__init__.py
microsoft_agents_m365copilot/_version.py
microsoft_agents_m365copilot/agents_m365_copilot_request_adapter.py
microsoft_agents_m365copilot/agents_m365_copilot_service_client.py
microsoft_agents_m365copilot/generated/base_agents_m365_copilot_service_client.py
microsoft_agents_m365copilot/generated/copilot/admin/admin_request_builder.py
microsoft_agents_m365copilot/generated/copilot/admin/settings/limited_mode/limited_mode_request_builder.py
microsoft_agents_m365copilot/generated/copilot/admin/settings/settings_request_builder.py
microsoft_agents_m365copilot/generated/copilot/copilot_request_builder.py
microsoft_agents_m365copilot/generated/copilot/interaction_history/get_all_enterprise_interactions/get_all_enterprise_interactions_get_response.py
microsoft_agents_m365copilot/generated/copilot/interaction_history/get_all_enterprise_interactions/get_all_enterprise_interactions_request_builder.py
microsoft_agents_m365copilot/generated/copilot/interaction_history/interaction_history_request_builder.py
microsoft_agents_m365copilot/generated/copilot/reports/get_microsoft365_copilot_usage_user_detail_with_period/get_microsoft365_copilot_usage_user_detail_with_period_request_builder.py
microsoft_agents_m365copilot/generated/copilot/reports/get_microsoft365_copilot_user_count_summary_with_period/get_microsoft365_copilot_user_count_summary_with_period_request_builder.py
microsoft_agents_m365copilot/generated/copilot/reports/get_microsoft365_copilot_user_count_trend_with_period/get_microsoft365_copilot_user_count_trend_with_period_request_builder.py
microsoft_agents_m365copilot/generated/copilot/reports/reports_request_builder.py
microsoft_agents_m365copilot/generated/copilot/retrieval/retrieval_post_request_body.py
microsoft_agents_m365copilot/generated/copilot/retrieval/retrieval_request_builder.py
microsoft_agents_m365copilot/generated/copilot/users/count/count_request_builder.py
microsoft_agents_m365copilot-1.4.0.dist-info/METADATA
microsoft_agents_m365copilot-1.4.0.dist-info/WHEEL
microsoft_agents_m365copilot-1.4.0.dist-info/RECORD
