Metadata-Version: 2.4
Name: microsoft-agents-m365copilot
Version: 1.4.0
Summary: Microsoft Agents M365 Copilot Python SDK (V1.0)
License: MIT
Keywords: copilot,openAPI,Microsoft,M365,V1.0
Author: Microsoft
Author-email: graphtooling+ccspython@microsoft.com
Maintainer: Microsoft
Maintainer-email: graphtooling+ccspython@microsoft.com
Requires-Python: >=3.9,<4.0
Classifier: Development Status :: 4 - Beta
Classifier: Intended Audience :: Developers
Classifier: License :: OSI Approved :: MIT License
Classifier: Operating System :: OS Independent
Classifier: Programming Language :: Python :: 3
Classifier: Programming Language :: Python :: 3.9
Classifier: Programming Language :: Python :: 3.10
Classifier: Programming Language :: Python :: 3.11
Classifier: Programming Language :: Python :: 3.12
Classifier: Programming Language :: Python :: 3.13
Classifier: Programming Language :: Python :: 3.14
Classifier: Topic :: Software Development :: Libraries :: Python Modules
Requires-Dist: httpx[http2] (>=0.23.0)
Requires-Dist: microsoft-agents-m365copilot-core (>=1.0.0rc1)
Requires-Dist: microsoft-kiota-authentication-azure (>=1.8.0,<2.0.0)
Requires-Dist: microsoft-kiota-bundle (>=1.8.0,<2.0.0)
Project-URL: Documentation, https://github.com/microsoft/Agents-M365Copilot/tree/main/python/packages/microsoft_agents_m365copilot#readme
Project-URL: Homepage, https://github.com/microsoft/Agents-M365Copilot/tree/main/python
Project-URL: Repository, https://github.com/microsoft/Agents-M365Copilot
